pdf_client_wrapper/__init__.py
pdf_client_wrapper/app_config.py
pdf_client_wrapper/client.py
pdf_client_wrapper/pts_render.py
pdf_client_wrapper/utils.py
pdf_client_wrapper/rpc/__init__.py
pdf_client_wrapper/rpc/pdf_pb2.py
pdf_client_wrapper/rpc/pdf_pb2_grpc.py
pdf_client_wrapper/rpc/xy_units_pb2.py
pdf_client_wrapper/rpc/xy_units_pb2_grpc.py
tests/__init__.py
tests/test_utils.py
pdf_client_wrapper-0.1.2.dist-info/METADATA
pdf_client_wrapper-0.1.2.dist-info/WHEEL
pdf_client_wrapper-0.1.2.dist-info/entry_points.txt
pdf_client_wrapper-0.1.2.dist-info/top_level.txt
pdf_client_wrapper-0.1.2.dist-info/RECORD
