Metadata-Version: 2.1
Name: pdf-client-wrapper
Version: 0.1.2
Summary: pdf client wrapper, more easy to use pdf-server
Home-page: https://e.coding.net/xymedimg/pdf-server/pdf-client-wrapper.git
Author: Daryl Xu
Author-email: xuziqiang@zyheal.com
License: UNKNOWN
Platform: UNKNOWN
Classifier: Programming Language :: Python :: 3.8
Classifier: Operating System :: OS Independent
Requires-Dist: source
Requires-Dist: grpcio
Requires-Dist: protobuf (<=3.20.3)
